setup.cfg
setup.py
workqueue/__init__.py
workqueue/work.py
workqueue.egg-info/PKG-INFO
workqueue.egg-info/SOURCES.txt
workqueue.egg-info/dependency_links.txt
workqueue.egg-info/requires.txt
workqueue.egg-info/top_level.txt