Metadata-Version: 1.1
Name: workqueue
Version: 0.1.0
Summary: Master/Worker implementation of a Task Queue
Home-page: https://github.com/adminMesfix/workqueue
Author: Jesus Martinez
Author-email: jesus.a.martinez.v@gmail.com
License: UNKNOWN
Download-URL: https://github.com/adminMesfix/workqueue/tarball/0.1.0
Keywords: task,queue,master,worker,async,asynchronous
Platform: UNKNOWN
